fulladder/adder.v
module full_adder(
    input a,
    input b,
    input cin,
    output sum,
    output cout
);

assign sum = a ^ b ^ cin;
assign cout = (a & b) | (b & cin) | (cin & a);
initial begin
  $dumpfile("dump.vcd");       // Creates a VCD waveform file
  $dumpvars(0, full_adder);    // Dumps all signals in the full_adder module
end
endmodule

fulladder/dump.vcd
$date
	Wed Jul 16 21:27:11 2025
$end
$version
	Icarus Verilog
$end
$timescale
	1ps
$end
$scope module full_adder $end
$var wire 1 ! a $end
$var wire 1 " b $end
$var wire 1 # cin $end
$var wire 1 $ cout $end
$var wire 1 % sum $end
$upscope $end
$enddefinitions $end
$comment Show the parameter values. $end
$dumpall
$end
#0
$dumpvars
0%
0$
0#
0"
0!
$end
#1000
1%
1#
#2000
0#
1"
#3000
1$
0%
1#
#4000
0$
1%
0#
0"
1!
#5000
1$
0%
1#
#6000
0#
1"
#7000
1%
1#
